sdre_cpp.cpython-37m-x86_64-linux-gnu.so
sdre_cpp-0.0.4.dist-info/RECORD
sdre_cpp-0.0.4.dist-info/METADATA
sdre_cpp-0.0.4.dist-info/LICENSE
sdre_cpp-0.0.4.dist-info/top_level.txt
sdre_cpp-0.0.4.dist-info/WHEEL
sdre_cpp.libs/libgomp-a34b3233.so.1.0.0
