Metadata-Version: 2.1
Name: sdre-cpp
Version: 0.0.4
Summary: Stochastic multi-stage birth process simulation
Author: Richard Paul
Author-email: richard@los-paul.eu
Requires-Python: >=3.7
License-File: LICENSE
Provides-Extra: test
Requires-Dist: pytest >=6.0 ; extra == 'test'
